guc_cms_scrapper.py
guc_cms_scrapper-0.2.5.dist-info/METADATA
guc_cms_scrapper-0.2.5.dist-info/WHEEL
guc_cms_scrapper-0.2.5.dist-info/RECORD
