Metadata-Version: 2.1
Name: guc-cms-scrapper
Version: 0.2.5
Summary: A package to scrap the GUC university CMS to get the courses and their details
Author: Mathew Hany
Author-email: mathew.hanybb@gmail.com
Requires-Python: >=3.11,<4.0
Classifier: Programming Language :: Python :: 3
Classifier: Programming Language :: Python :: 3.11
Classifier: Programming Language :: Python :: 3.12
Requires-Dist: beautifulsoup4 (>=4.12.3,<5.0.0)
Requires-Dist: google-generativeai (>=0.8.3,<0.9.0)
Requires-Dist: requests (>=2.32.3,<3.0.0)
Requires-Dist: requests-ntlm (>=1.3.0,<2.0.0)
